pymgcv/__init__.py
pymgcv/basis_functions.py
pymgcv/custom_types.py
pymgcv/families.py
pymgcv/formula_utils.py
pymgcv/gam.py
pymgcv/plot.py
pymgcv/qq.py
pymgcv/rlibs.py
pymgcv/rpy_utils.py
pymgcv/terms.py
pymgcv/utils.py
pymgcv-0.0.10.dist-info/METADATA
pymgcv-0.0.10.dist-info/WHEEL
pymgcv-0.0.10.dist-info/licenses/LICENSE
pymgcv-0.0.10.dist-info/RECORD
