Metadata-Version: 2.4
Name: pymgcv
Version: 0.0.10
Summary: pymgcv: Generalized additive models using mgcv, in Python.
Author-email: danielward27 <danielward27@outlook.com>
License:   GNU GENERAL PUBLIC LICENSE
License-File: LICENSE
Keywords: GAMs,generalized additive models
Requires-Python: >=3.11
Requires-Dist: matplotlib>=3.10
Requires-Dist: numpy>=2.2.5
Requires-Dist: pandas>=2.2.3
Requires-Dist: rpy2>=3.6.2
Requires-Dist: scipy>=1.12.0
Provides-Extra: dev
Requires-Dist: build; extra == 'dev'
Requires-Dist: griffe-inherited-docstrings; extra == 'dev'
Requires-Dist: ipykernel; extra == 'dev'
Requires-Dist: markdown-it-py; extra == 'dev'
Requires-Dist: mdit-py-plugins; extra == 'dev'
Requires-Dist: mkdocs; extra == 'dev'
Requires-Dist: mkdocs-ipynb; extra == 'dev'
Requires-Dist: mkdocs-material; extra == 'dev'
Requires-Dist: mkdocstrings[python]; extra == 'dev'
Requires-Dist: nbconvert; extra == 'dev'
Requires-Dist: pymdown-extensions; extra == 'dev'
Requires-Dist: pytest; extra == 'dev'
Requires-Dist: pytest-markdown-docs; extra == 'dev'
Requires-Dist: ruff; extra == 'dev'
